{
    "autoVolumeSrc": {
        "cargoLocks": null,
        "date": "2020-02-16",
        "extract": null,
        "name": "autoVolumeSrc",
        "passthru": null,
        "pinned": false,
        "src": {
            "deepClone": false,
            "fetchSubmodules": false,
            "leaveDotGit": false,
            "name": null,
            "rev": "d7f7962724b567a8409ef2898602f2c57abddf5a",
            "sha256": "sha256-WquDmeaj+7M8DzGuHYOJgF6ifcs3vj3gIciZMaRQ3t4=",
            "sparseCheckout": [],
            "type": "git",
            "url": "https://github.com/amanharwara/spicetify-autoVolume"
        },
        "version": "d7f7962724b567a8409ef2898602f2c57abddf5a"
    },
    "bloomSrc": {
        "cargoLocks": null,
        "date": "2024-09-09",
        "extract": null,
        "name": "bloomSrc",
        "passthru": null,
        "pinned": false,
        "src": {
            "deepClone": false,
            "fetchSubmodules": false,
            "leaveDotGit": false,
            "name": null,
            "rev": "809c042ca8f88540604fbd6aca35f42bddfcaf27",
            "sha256": "sha256-dyCCpTiLAqObeHEfmwT89J52NB3M2L17/E5klIXMTec=",
            "sparseCheckout": [],
            "type": "git",
            "url": "https://github.com/nimsandu/spicetify-bloom"
        },
        "version": "809c042ca8f88540604fbd6aca35f42bddfcaf27"
    },
    "catppuccinSrc": {
        "cargoLocks": null,
        "date": "2024-05-20",
        "extract": null,
        "name": "catppuccinSrc",
        "passthru": null,
        "pinned": false,
        "src": {
            "deepClone": false,
            "fetchSubmodules": false,
            "leaveDotGit": false,
            "name": null,
            "rev": "4294a61f54a044768c6e9db20e83c5b74da71091",
            "sha256": "sha256-OHsauoCjj99aoIbq78xQf1ehYtLpIcUde5DmZSJFCXI=",
            "sparseCheckout": [],
            "type": "git",
            "url": "https://github.com/catppuccin/spicetify"
        },
        "version": "4294a61f54a044768c6e9db20e83c5b74da71091"
    },
    "charlieS1103Src": {
        "cargoLocks": null,
        "date": "2024-05-13",
        "extract": null,
        "name": "charlieS1103Src",
        "passthru": null,
        "pinned": false,
        "src": {
            "deepClone": false,
            "fetchSubmodules": false,
            "leaveDotGit": false,
            "name": null,
            "rev": "ab8fe9ccabc86477bc55a561fc532a0fa416d58c",
            "sha256": "sha256-14Q1hHowE0w9ynpjlM6rM079Hqu1WVy3dzarwCZSXHE=",
            "sparseCheckout": [],
            "type": "git",
            "url": "https://github.com/CharlieS1103/spicetify-extensions"
        },
        "version": "ab8fe9ccabc86477bc55a561fc532a0fa416d58c"
    },
    "comfySrc": {
        "cargoLocks": null,
        "date": "2024-12-03",
        "extract": null,
        "name": "comfySrc",
        "passthru": null,
        "pinned": false,
        "src": {
            "deepClone": false,
            "fetchSubmodules": false,
            "leaveDotGit": false,
            "name": null,
            "rev": "b5fbe9f01feed5081b74b678076bed4a59801185",
            "sha256": "sha256-clq21blMlQVrt6h0tW3wdSMNAUPaOo10XExWofimK1o=",
            "sparseCheckout": [],
            "type": "git",
            "url": "https://github.com/Comfy-Themes/Spicetify"
        },
        "version": "b5fbe9f01feed5081b74b678076bed4a59801185"
    },
    "customAppsExtensionsSrc": {
        "cargoLocks": null,
        "date": "2024-11-07",
        "extract": null,
        "name": "customAppsExtensionsSrc",
        "passthru": null,
        "pinned": false,
        "src": {
            "deepClone": false,
            "fetchSubmodules": false,
            "leaveDotGit": false,
            "name": null,
            "rev": "bb12c53dc11413e980ce3e40fbcec6f23b752003",
            "sha256": "sha256-7kVG5rAGKr8FTtXG7h0V2dBd8MBG5ntBwOjANN2Oheg=",
            "sparseCheckout": [],
            "type": "git",
            "url": "https://github.com/3raxton/spicetify-custom-apps-and-extensions"
        },
        "version": "bb12c53dc11413e980ce3e40fbcec6f23b752003"
    },
    "dakshExtensions": {
        "cargoLocks": null,
        "date": "2024-12-19",
        "extract": null,
        "name": "dakshExtensions",
        "passthru": null,
        "pinned": false,
        "src": {
            "deepClone": false,
            "fetchSubmodules": false,
            "leaveDotGit": false,
            "name": null,
            "rev": "ebc25a3543efaf864993324f5981b3bda3eaf2d8",
            "sha256": "sha256-qZf1VTxQhac5qU4oLBy9fi7es1NhDJ1DDIvk1zbdhZE=",
            "sparseCheckout": [],
            "type": "git",
            "url": "https://github.com/daksh2k/Spicetify-stuff"
        },
        "version": "ebc25a3543efaf864993324f5981b3bda3eaf2d8"
    },
    "defaultDynamicSrc": {
        "cargoLocks": null,
        "date": "2024-12-21",
        "extract": null,
        "name": "defaultDynamicSrc",
        "passthru": null,
        "pinned": false,
        "src": {
            "deepClone": false,
            "fetchSubmodules": false,
            "leaveDotGit": false,
            "name": null,
            "rev": "adffce4aefe52adbc8fe80644235e65acf402c46",
            "sha256": "sha256-lBm8TFqyo6YXjgo/PKRfIQeRSfKVskHNtXoStoTevKA=",
            "sparseCheckout": [],
            "type": "git",
            "url": "https://github.com/JulienMaille/spicetify-dynamic-theme"
        },
        "version": "adffce4aefe52adbc8fe80644235e65acf402c46"
    },
    "draculaSrc": {
        "cargoLocks": null,
        "date": "2022-02-14",
        "extract": null,
        "name": "draculaSrc",
        "passthru": null,
        "pinned": false,
        "src": {
            "deepClone": false,
            "fetchSubmodules": false,
            "leaveDotGit": false,
            "name": null,
            "rev": "97bf149e7afbe408509862591a57f1d8e2dfc5d7",
            "sha256": "sha256-IS0A/5zTZou9yQJ0zpqAwiW2COt/TGoscN99WGFR9FA=",
            "sparseCheckout": [],
            "type": "git",
            "url": "https://github.com/Darkempire78/Dracula-Spicetify"
        },
        "version": "97bf149e7afbe408509862591a57f1d8e2dfc5d7"
    },
    "eternalJukeboxSrc": {
        "cargoLocks": null,
        "date": "2025-01-13",
        "extract": null,
        "name": "eternalJukeboxSrc",
        "passthru": null,
        "pinned": false,
        "src": {
            "deepClone": false,
            "fetchSubmodules": false,
            "leaveDotGit": false,
            "name": null,
            "rev": "63fcfce9bac7de59ca9cd06908c63705c8611625",
            "sha256": "sha256-mz358KeCsVJbrYhY+3fWbHhZkn9UbTM3uxv5wc8hltk=",
            "sparseCheckout": [],
            "type": "git",
            "url": "https://github.com/Pithaya/spicetify-apps-dist"
        },
        "version": "63fcfce9bac7de59ca9cd06908c63705c8611625"
    },
    "fluentSrc": {
        "cargoLocks": null,
        "date": "2024-05-02",
        "extract": null,
        "name": "fluentSrc",
        "passthru": null,
        "pinned": false,
        "src": {
            "deepClone": false,
            "fetchSubmodules": false,
            "leaveDotGit": false,
            "name": null,
            "rev": "64b946af1ee4a5ed761d2f065c45b710e06bc123",
            "sha256": "sha256-M6kczYmo0/+yL6iuMgkXECIQLOXDIR1aY8htS4KWjCE=",
            "sparseCheckout": [],
            "type": "git",
            "url": "https://github.com/williamckha/spicetify-fluent"
        },
        "version": "64b946af1ee4a5ed761d2f065c45b710e06bc123"
    },
    "groupSessionSrc": {
        "cargoLocks": null,
        "date": "2024-10-12",
        "extract": null,
        "name": "groupSessionSrc",
        "passthru": null,
        "pinned": false,
        "src": {
            "deepClone": false,
            "fetchSubmodules": false,
            "leaveDotGit": false,
            "name": null,
            "rev": "e6a2ce35589b9404e539c5778fa1c2efa53eefe6",
            "sha256": "sha256-+DMtll5VGFkQIeeH+WklPow0iRzz0Sv1I/N8Gt4vzyQ=",
            "sparseCheckout": [],
            "type": "git",
            "url": "https://github.com/timll/spotify-group-session"
        },
        "version": "e6a2ce35589b9404e539c5778fa1c2efa53eefe6"
    },
    "hidePodcastsSrc": {
        "cargoLocks": null,
        "date": "2025-01-01",
        "extract": null,
        "name": "hidePodcastsSrc",
        "passthru": null,
        "pinned": false,
        "src": {
            "deepClone": false,
            "fetchSubmodules": false,
            "leaveDotGit": false,
            "name": null,
            "rev": "36ed07c460cab47cb352b2e2fd493b00df1eabaf",
            "sha256": "sha256-iLifViDyIBmJot2UjWVpMywv+iwKK4gtGYPD/J/eyRc=",
            "sparseCheckout": [],
            "type": "git",
            "url": "https://github.com/theRealPadster/spicetify-hide-podcasts"
        },
        "version": "36ed07c460cab47cb352b2e2fd493b00df1eabaf"
    },
    "historySrc": {
        "cargoLocks": null,
        "date": "2021-05-20",
        "extract": null,
        "name": "historySrc",
        "passthru": null,
        "pinned": false,
        "src": {
            "deepClone": false,
            "fetchSubmodules": false,
            "leaveDotGit": false,
            "name": null,
            "rev": "577e34f364127f18d917d2fe2e8c8f2a1af9f6ae",
            "sha256": "sha256-ORG1oNvMTJxrI3spfAuN+pCKTKvQfhqUIYT9NM1yZTs=",
            "sparseCheckout": [],
            "type": "git",
            "url": "https://github.com/einzigartigerName/spicetify-history"
        },
        "version": "577e34f364127f18d917d2fe2e8c8f2a1af9f6ae"
    },
    "huhExtensionsSrc": {
        "cargoLocks": null,
        "date": "2024-10-31",
        "extract": null,
        "name": "huhExtensionsSrc",
        "passthru": null,
        "pinned": false,
        "src": {
            "deepClone": false,
            "fetchSubmodules": false,
            "leaveDotGit": false,
            "name": null,
            "rev": "d58201e27716df86ace457a82dce980175c2d65d",
            "sha256": "sha256-ZJJC7mGsM6H8rEfX82CF0kkv/2MYHehN+nS7FktV/t4=",
            "sparseCheckout": [],
            "type": "git",
            "url": "https://github.com/huhridge/huh-spicetify-extensions"
        },
        "version": "d58201e27716df86ace457a82dce980175c2d65d"
    },
    "lastfmSrc": {
        "cargoLocks": null,
        "date": "2022-11-20",
        "extract": null,
        "name": "lastfmSrc",
        "passthru": null,
        "pinned": false,
        "src": {
            "deepClone": false,
            "fetchSubmodules": false,
            "leaveDotGit": false,
            "name": null,
            "rev": "d2f1d3c1e286d789ddfa002f162405782d822c55",
            "sha256": "sha256-/C4Y3zuSAEwhMXCRG2/4b5oWfGz/ij6wu0B+CpuJKXs=",
            "sparseCheckout": [],
            "type": "git",
            "url": "https://github.com/LucasBares/spicetify-last-fm"
        },
        "version": "d2f1d3c1e286d789ddfa002f162405782d822c55"
    },
    "localFilesSrc": {
        "cargoLocks": null,
        "date": "2022-04-12",
        "extract": null,
        "name": "localFilesSrc",
        "passthru": null,
        "pinned": false,
        "src": {
            "deepClone": false,
            "fetchSubmodules": false,
            "leaveDotGit": false,
            "name": null,
            "rev": "1bfd2fc80385b21ed6dd207b00a371065e53042e",
            "sha256": "sha256-neKR2WaZ1K10dZZ0nAKJJEHNS56o8vCpYpi+ZJYJ/gU=",
            "sparseCheckout": [],
            "type": "git",
            "url": "https://github.com/hroland/spicetify-show-local-files"
        },
        "version": "1bfd2fc80385b21ed6dd207b00a371065e53042e"
    },
    "marketplaceSrc": {
        "cargoLocks": null,
        "date": "2025-02-01",
        "extract": null,
        "name": "marketplaceSrc",
        "passthru": null,
        "pinned": false,
        "src": {
            "deepClone": false,
            "fetchSubmodules": false,
            "leaveDotGit": false,
            "name": null,
            "rev": "2c793ebb7974c6cc1ecb58d3d514389d9deb324a",
            "sha256": "sha256-gh8a3BTkBtLztgAwTBSq8DeXTIcfLJqacE5k8WVMOsE=",
            "sparseCheckout": [],
            "type": "git",
            "url": "https://github.com/spicetify/spicetify-marketplace"
        },
        "version": "2c793ebb7974c6cc1ecb58d3d514389d9deb324a"
    },
    "nameThatTuneSrc": {
        "cargoLocks": null,
        "date": "2025-01-01",
        "extract": null,
        "name": "nameThatTuneSrc",
        "passthru": null,
        "pinned": false,
        "src": {
            "deepClone": false,
            "fetchSubmodules": false,
            "leaveDotGit": false,
            "name": null,
            "rev": "858b98baa97e486a8589b26164c9eb1aa3605282",
            "sha256": "sha256-fBdR6foZGM+YPv52TBhhF0qPDDsgflD6viWebOZcY4Y=",
            "sparseCheckout": [],
            "type": "git",
            "url": "https://github.com/theRealPadster/name-that-tune"
        },
        "version": "858b98baa97e486a8589b26164c9eb1aa3605282"
    },
    "nordSrc": {
        "cargoLocks": null,
        "date": "2023-06-06",
        "extract": null,
        "name": "nordSrc",
        "passthru": null,
        "pinned": false,
        "src": {
            "deepClone": false,
            "fetchSubmodules": false,
            "leaveDotGit": false,
            "name": null,
            "rev": "caab9e0afaa6d228b4d73ae6c4c40dd56d3888c7",
            "sha256": "sha256-HlywN6a6nQ9Z1Rsg3crkFQuY+npXaN4Qo9cjPLfeqmw=",
            "sparseCheckout": [],
            "type": "git",
            "url": "https://github.com/Tetrax-10/Nord-Spotify"
        },
        "version": "caab9e0afaa6d228b4d73ae6c4c40dd56d3888c7"
    },
    "officialSrc": {
        "cargoLocks": null,
        "date": "2025-02-05",
        "extract": null,
        "name": "officialSrc",
        "passthru": null,
        "pinned": false,
        "src": {
            "deepClone": false,
            "fetchSubmodules": false,
            "leaveDotGit": false,
            "name": null,
            "rev": "7f649dae6f1a04d6a7c76c381da8a436d6990576",
            "sha256": "sha256-Ztv4uYRalOgRd4/5n/XgDxgp2U9xXz7Wa/ypyDYT5s8=",
            "sparseCheckout": [],
            "type": "git",
            "url": "https://github.com/spicetify/spicetify-cli"
        },
        "version": "7f649dae6f1a04d6a7c76c381da8a436d6990576"
    },
    "officialThemes": {
        "cargoLocks": null,
        "date": "2024-12-04",
        "extract": null,
        "name": "officialThemes",
        "passthru": null,
        "pinned": false,
        "src": {
            "deepClone": false,
            "fetchSubmodules": false,
            "leaveDotGit": false,
            "name": null,
            "rev": "ca4264263a51800a119fa0bea231f25f58857d5f",
            "sha256": "sha256-f1oqEKH594LTACGzw6ZUQpgZqyHLeMz8HBvAfY5ub00=",
            "sparseCheckout": [],
            "type": "git",
            "url": "https://github.com/spicetify/spicetify-themes"
        },
        "version": "ca4264263a51800a119fa0bea231f25f58857d5f"
    },
    "omniSrc": {
        "cargoLocks": null,
        "date": "2023-01-20",
        "extract": null,
        "name": "omniSrc",
        "passthru": null,
        "pinned": false,
        "src": {
            "deepClone": false,
            "fetchSubmodules": false,
            "leaveDotGit": false,
            "name": null,
            "rev": "253ae45d2cac2dc3d92a43193ea8f6d9e7e1d3aa",
            "sha256": "sha256-5II+4096fOcCA7J4XZfIHSse+3/YJ+EY5KW3GXl+dn8=",
            "sparseCheckout": [],
            "type": "git",
            "url": "https://github.com/getomni/spicetify"
        },
        "version": "253ae45d2cac2dc3d92a43193ea8f6d9e7e1d3aa"
    },
    "orchisSrc": {
        "cargoLocks": null,
        "date": "2022-05-20",
        "extract": null,
        "name": "orchisSrc",
        "passthru": null,
        "pinned": false,
        "src": {
            "deepClone": false,
            "fetchSubmodules": false,
            "leaveDotGit": false,
            "name": null,
            "rev": "5bf3fcf0696514dcf3e95f4ae3fd00261ccc5dcc",
            "sha256": "sha256-9cU2Wlg5W57JpBfzIOXvpRYI8Q3CsH+UsdjQseTr9bs=",
            "sparseCheckout": [],
            "type": "git",
            "url": "https://github.com/canbeardig/Spicetify-Orchis-Colours-v2"
        },
        "version": "5bf3fcf0696514dcf3e95f4ae3fd00261ccc5dcc"
    },
    "playlistIconsSrc": {
        "cargoLocks": null,
        "date": "2024-12-01",
        "extract": null,
        "name": "playlistIconsSrc",
        "passthru": null,
        "pinned": false,
        "src": {
            "deepClone": false,
            "fetchSubmodules": false,
            "leaveDotGit": false,
            "name": null,
            "rev": "7378f0a823eabf1b1a5f9b6237002dcd4631a27a",
            "sha256": "sha256-EBl8mSofEdjAoHugziLDF/5FRSoCfpW9wIj3HH4iwkA=",
            "sparseCheckout": [],
            "type": "git",
            "url": "https://github.com/jeroentvb/spicetify-playlist-icons"
        },
        "version": "7378f0a823eabf1b1a5f9b6237002dcd4631a27a"
    },
    "powerBarSrc": {
        "cargoLocks": null,
        "date": "2024-12-01",
        "extract": null,
        "name": "powerBarSrc",
        "passthru": null,
        "pinned": false,
        "src": {
            "deepClone": false,
            "fetchSubmodules": false,
            "leaveDotGit": false,
            "name": null,
            "rev": "39be3f3f2626d30b210cc7cea9815a3933d1ab99",
            "sha256": "sha256-OhhHv7Av6IGxihSZtQ2zekSD8IAIfC2Ny1qghwFraII=",
            "sparseCheckout": [],
            "type": "git",
            "url": "https://github.com/jeroentvb/spicetify-power-bar"
        },
        "version": "39be3f3f2626d30b210cc7cea9815a3933d1ab99"
    },
    "retroBlurSrc": {
        "cargoLocks": null,
        "date": "2024-06-08",
        "extract": null,
        "name": "retroBlurSrc",
        "passthru": null,
        "pinned": false,
        "src": {
            "deepClone": false,
            "fetchSubmodules": false,
            "leaveDotGit": false,
            "name": null,
            "rev": "685cf3aea4ed1a4d82f687293f0efb5baa1aec06",
            "sha256": "sha256-YAOmeSAxD0qR8Y7t+HOBoTCJtiJNfveJCmiptfg25OE=",
            "sparseCheckout": [],
            "type": "git",
            "url": "https://github.com/Motschen/Retroblur"
        },
        "version": "685cf3aea4ed1a4d82f687293f0efb5baa1aec06"
    },
    "spicetifyStatsSrc": {
        "cargoLocks": null,
        "date": "2024-07-08",
        "extract": null,
        "name": "spicetifyStatsSrc",
        "passthru": null,
        "pinned": false,
        "src": {
            "deepClone": false,
            "fetchSubmodules": false,
            "leaveDotGit": false,
            "name": null,
            "rev": "0a82d88e5517f21595c641c60015671dacb1d7fe",
            "sha256": "sha256-JqJGLL96eABeV9Trp0Gevmjw8FqazCLu+9fsRvMR/KI=",
            "sparseCheckout": [],
            "type": "git",
            "url": "https://github.com/harbassan/spicetify-stats"
        },
        "version": "0a82d88e5517f21595c641c60015671dacb1d7fe"
    },
    "spotifyCanvasSrc": {
        "cargoLocks": null,
        "date": "2024-03-03",
        "extract": null,
        "name": "spotifyCanvasSrc",
        "passthru": null,
        "pinned": false,
        "src": {
            "deepClone": false,
            "fetchSubmodules": false,
            "leaveDotGit": false,
            "name": null,
            "rev": "d3fd4a3ef31726bc9b9f5192bc7f4e6bc2f98e6c",
            "sha256": "sha256-QhhxZo2V+jhJfsEM+TFTzHb6A5ddnsyTJdDgtshSpk8=",
            "sparseCheckout": [],
            "type": "git",
            "url": "https://github.com/itsmeow/Spicetify-Canvas"
        },
        "version": "d3fd4a3ef31726bc9b9f5192bc7f4e6bc2f98e6c"
    },
    "spotifyNoPremiumSrc": {
        "cargoLocks": null,
        "date": "2024-11-11",
        "extract": null,
        "name": "spotifyNoPremiumSrc",
        "passthru": null,
        "pinned": false,
        "src": {
            "deepClone": false,
            "fetchSubmodules": false,
            "leaveDotGit": false,
            "name": null,
            "rev": "6b145fb84e16cdaea8f06aef4d1cfc0d6f5898e5",
            "sha256": "sha256-pjIBh40SnUgyAKGwVRKod2ac8+uqGJ2WSTnOYc9UnGA=",
            "sparseCheckout": [],
            "type": "git",
            "url": "https://github.com/Daksh777/SpotifyNoPremium"
        },
        "version": "6b145fb84e16cdaea8f06aef4d1cfc0d6f5898e5"
    },
    "spotifywmSrc": {
        "cargoLocks": null,
        "date": "2022-10-25",
        "extract": null,
        "name": "spotifywmSrc",
        "passthru": null,
        "pinned": false,
        "src": {
            "deepClone": false,
            "fetchSubmodules": false,
            "leaveDotGit": false,
            "name": null,
            "rev": "8624f539549973c124ed18753881045968881745",
            "sha256": "sha256-AsXqcoqUXUFxTG+G+31lm45gjP6qGohEnUSUtKypew0=",
            "sparseCheckout": [],
            "type": "git",
            "url": "https://github.com/dasJ/spotifywm"
        },
        "version": "8624f539549973c124ed18753881045968881745"
    },
    "startPageSrc": {
        "cargoLocks": null,
        "date": "2024-02-15",
        "extract": null,
        "name": "startPageSrc",
        "passthru": null,
        "pinned": false,
        "src": {
            "deepClone": false,
            "fetchSubmodules": false,
            "leaveDotGit": false,
            "name": null,
            "rev": "75bd17ba1c9a19730f14529fb18857d7b9c7c12e",
            "sha256": "sha256-+Th5o00c3Y8U+Y/RGmRSkWWp97YCoCJmoESFLZf9dwM=",
            "sparseCheckout": [],
            "type": "git",
            "url": "https://github.com/Resxt/startup-page"
        },
        "version": "75bd17ba1c9a19730f14529fb18857d7b9c7c12e"
    },
    "tetraxSrc": {
        "cargoLocks": null,
        "date": "2023-07-22",
        "extract": null,
        "name": "tetraxSrc",
        "passthru": null,
        "pinned": false,
        "src": {
            "deepClone": false,
            "fetchSubmodules": false,
            "leaveDotGit": false,
            "name": null,
            "rev": "a224969550b3831c4fb084bcc8c675f3a77735d1",
            "sha256": "sha256-XT0l6DVaXXaD7QihilpF3vQ+kry98sss3POR5gTRmhI=",
            "sparseCheckout": [],
            "type": "git",
            "url": "https://github.com/Tetrax-10/Spicetify-Extensions"
        },
        "version": "a224969550b3831c4fb084bcc8c675f3a77735d1"
    }
}